{
    "GREEDY_MAJ": {
        "GREEDY_WMAJ": {
            "wins": 16,
            "winsB": 9,
            "winsW": 7,
            "losses": 79,
            "lossesB": 35,
            "lossesW": 44,
            "ties": 3,
            "tiesB": 0,
            "tiesW": 3,
            "total": 98,
            "winpct": 16,
            "winpctB": 20,
            "losepct": 80,
            "losepctW": 81,
            "losepctB": 79,
            "tiepct": 3,
            "tiepctW": 5,
            "winpctW": 12,
            "tiepctB": 0
        },
        "GREEDY_MAJ": {
            "wins": 59,
            "winsB": 29,
            "winsW": 30,
            "losses": 59,
            "lossesB": 30,
            "lossesW": 29,
            "ties": 4,
            "tiesB": 2,
            "tiesW": 2,
            "total": 122,
            "winpct": 48,
            "winpctB": 47,
            "losepct": 48,
            "losepctW": 47,
            "losepctB": 49,
            "tiepct": 3,
            "tiepctW": 3,
            "winpctW": 49,
            "tiepctB": 3
        },
        "RANDOM": {
            "wins": 65,
            "winsB": 29,
            "winsW": 36,
            "losses": 39,
            "lossesB": 24,
            "lossesW": 15,
            "ties": 3,
            "tiesB": 1,
            "tiesW": 2,
            "total": 107,
            "winpct": 60,
            "winpctB": 53,
            "losepct": 36,
            "losepctW": 28,
            "losepctB": 44,
            "tiepct": 2,
            "tiepctW": 3,
            "winpctW": 67,
            "tiepctB": 1
        },
        "PMC": {
            "wins": 3,
            "winsB": 3,
            "winsW": 0,
            "losses": 4,
            "lossesB": 3,
            "lossesW": 1,
            "ties": 0,
            "tiesB": 0,
            "tiesW": 0,
            "total": 7,
            "winpct": 42,
            "winpctB": 50,
            "losepct": 57,
            "losepctW": 100,
            "losepctB": 50,
            "tiepct": 0,
            "tiepctW": 0,
            "winpctW": 0,
            "tiepctB": 0
        },
        "MCTS": {
            "wins": 0,
            "winsB": 0,
            "winsW": 0,
            "losses": 7,
            "lossesB": 3,
            "lossesW": 4,
            "ties": 0,
            "tiesB": 0,
            "tiesW": 0,
            "total": 7,
            "winpct": 0,
            "winpctB": 0,
            "losepct": 100,
            "losepctW": 100,
            "losepctB": 100,
            "tiepct": 0,
            "tiepctW": 0,
            "winpctW": 0,
            "tiepctB": 0
        },
        "ab": {
            "wins": 4,
            "winsB": 1,
            "winsW": 3,
            "losses": 7,
            "lossesB": 5,
            "lossesW": 2,
            "ties": 0,
            "tiesB": 0,
            "tiesW": 0,
            "total": 11,
            "winpct": 36,
            "winpctB": 16,
            "losepct": 63,
            "losepctW": 40,
            "losepctB": 83,
            "tiepct": 0,
            "tiepctW": 0,
            "winpctW": 60,
            "tiepctB": 0
        }
    },
    "RANDOM": {
        "GREEDY_MAJ": {
            "wins": 39,
            "winsB": 15,
            "winsW": 24,
            "losses": 65,
            "lossesB": 36,
            "lossesW": 29,
            "ties": 3,
            "tiesB": 2,
            "tiesW": 1,
            "total": 107,
            "winpct": 36,
            "losepct": 60,
            "tiepct": 2,
            "winpctW": 44,
            "losepctW": 53,
            "tiepctW": 1,
            "winpctB": 28,
            "losepctB": 67,
            "tiepctB": 3
        },
        "RANDOM": {
            "wins": 45,
            "winsB": 18,
            "winsW": 27,
            "losses": 45,
            "lossesB": 27,
            "lossesW": 18,
            "ties": 0,
            "tiesB": 0,
            "tiesW": 0,
            "total": 90,
            "winpct": 50,
            "winpctB": 40,
            "losepct": 50,
            "losepctW": 40,
            "losepctB": 60,
            "tiepct": 0,
            "tiepctW": 0,
            "winpctW": 60,
            "tiepctB": 0
        },
        "GREEDY_WMAJ": {
            "wins": 20,
            "winsB": 7,
            "winsW": 13,
            "losses": 76,
            "lossesB": 34,
            "lossesW": 42,
            "ties": 2,
            "tiesB": 1,
            "tiesW": 1,
            "total": 98,
            "winpct": 20,
            "winpctB": 16,
            "losepct": 77,
            "losepctW": 75,
            "losepctB": 80,
            "tiepct": 2,
            "tiepctW": 1,
            "winpctW": 23,
            "tiepctB": 2
        },
        "PMC": {
            "wins": 1,
            "winsB": 1,
            "winsW": 0,
            "losses": 11,
            "lossesB": 9,
            "lossesW": 2,
            "ties": 0,
            "tiesB": 0,
            "tiesW": 0,
            "total": 12,
            "winpct": 8,
            "winpctB": 10,
            "losepct": 91,
            "losepctW": 100,
            "losepctB": 90,
            "tiepct": 0,
            "tiepctW": 0,
            "winpctW": 0,
            "tiepctB": 0
        },
        "MCTS": {
            "wins": 2,
            "winsB": 1,
            "winsW": 1,
            "losses": 6,
            "lossesB": 3,
            "lossesW": 3,
            "ties": 0,
            "tiesB": 0,
            "tiesW": 0,
            "total": 8,
            "winpct": 25,
            "winpctB": 25,
            "losepct": 75,
            "losepctW": 75,
            "losepctB": 75,
            "tiepct": 0,
            "tiepctW": 0,
            "winpctW": 25,
            "tiepctB": 0
        },
        "ab": {
            "wins": 2,
            "winsB": 1,
            "winsW": 1,
            "losses": 3,
            "lossesB": 1,
            "lossesW": 2,
            "ties": 1,
            "tiesB": 0,
            "tiesW": 1,
            "total": 6,
            "winpct": 33,
            "winpctB": 50,
            "losepct": 50,
            "losepctW": 50,
            "losepctB": 50,
            "tiepct": 16,
            "tiepctW": 25,
            "winpctW": 25,
            "tiepctB": 0
        }
    },
    "GREEDY_WMAJ": {
        "GREEDY_MAJ": {
            "wins": 79,
            "winsB": 44,
            "winsW": 35,
            "losses": 16,
            "lossesB": 7,
            "lossesW": 9,
            "ties": 3,
            "tiesB": 3,
            "tiesW": 0,
            "total": 98,
            "winpct": 80,
            "losepct": 16,
            "tiepct": 3,
            "winpctW": 79,
            "losepctW": 20,
            "tiepctW": 0,
            "winpctB": 81,
            "losepctB": 12,
            "tiepctB": 5
        },
        "RANDOM": {
            "wins": 76,
            "winsB": 42,
            "winsW": 34,
            "losses": 20,
            "lossesB": 13,
            "lossesW": 7,
            "ties": 2,
            "tiesB": 1,
            "tiesW": 1,
            "total": 98,
            "winpct": 77,
            "losepct": 20,
            "tiepct": 2,
            "winpctW": 80,
            "losepctW": 16,
            "tiepctW": 2,
            "winpctB": 75,
            "losepctB": 23,
            "tiepctB": 1
        },
        "GREEDY_WMAJ": {
            "wins": 49,
            "winsB": 26,
            "winsW": 23,
            "losses": 49,
            "lossesB": 23,
            "lossesW": 26,
            "ties": 0,
            "tiesB": 0,
            "tiesW": 0,
            "total": 98,
            "winpct": 50,
            "winpctB": 53,
            "losepct": 50,
            "losepctW": 53,
            "losepctB": 46,
            "tiepct": 0,
            "tiepctW": 0,
            "winpctW": 46,
            "tiepctB": 0
        },
        "PMC": {
            "wins": 11,
            "winsB": 5,
            "winsW": 6,
            "losses": 12,
            "lossesB": 8,
            "lossesW": 4,
            "ties": 0,
            "tiesB": 0,
            "tiesW": 0,
            "total": 23,
            "winpct": 47,
            "winpctB": 38,
            "losepct": 52,
            "losepctW": 40,
            "losepctB": 61,
            "tiepct": 0,
            "tiepctW": 0,
            "winpctW": 60,
            "tiepctB": 0
        },
        "MCTS": {
            "wins": 12,
            "winsB": 3,
            "winsW": 9,
            "losses": 30,
            "lossesB": 18,
            "lossesW": 12,
            "ties": 0,
            "tiesB": 0,
            "tiesW": 0,
            "total": 42,
            "winpct": 28,
            "winpctB": 14,
            "losepct": 71,
            "losepctW": 57,
            "losepctB": 85,
            "tiepct": 0,
            "tiepctW": 0,
            "winpctW": 42,
            "tiepctB": 0
        },
        "ab": {
            "wins": 15,
            "winsB": 6,
            "winsW": 9,
            "losses": 6,
            "lossesB": 2,
            "lossesW": 4,
            "ties": 1,
            "tiesB": 0,
            "tiesW": 1,
            "total": 22,
            "winpct": 68,
            "winpctB": 75,
            "losepct": 27,
            "losepctW": 28,
            "losepctB": 25,
            "tiepct": 4,
            "tiepctW": 7,
            "winpctW": 64,
            "tiepctB": 0
        }
    },
    "PMC": {
        "GREEDY_MAJ": {
            "wins": 4,
            "winsB": 1,
            "winsW": 3,
            "losses": 3,
            "lossesB": 0,
            "lossesW": 3,
            "ties": 0,
            "tiesB": 0,
            "tiesW": 0,
            "total": 7,
            "winpct": 57,
            "losepct": 42,
            "tiepct": 0,
            "winpctW": 50,
            "losepctW": 50,
            "tiepctW": 0,
            "winpctB": 100,
            "losepctB": 0,
            "tiepctB": 0
        },
        "RANDOM": {
            "wins": 11,
            "winsB": 2,
            "winsW": 9,
            "losses": 1,
            "lossesB": 0,
            "lossesW": 1,
            "ties": 0,
            "tiesB": 0,
            "tiesW": 0,
            "total": 12,
            "winpct": 91,
            "losepct": 8,
            "tiepct": 0,
            "winpctW": 90,
            "losepctW": 10,
            "tiepctW": 0,
            "winpctB": 100,
            "losepctB": 0,
            "tiepctB": 0
        },
        "GREEDY_WMAJ": {
            "wins": 12,
            "winsB": 4,
            "winsW": 8,
            "losses": 11,
            "lossesB": 6,
            "lossesW": 5,
            "ties": 0,
            "tiesB": 0,
            "tiesW": 0,
            "total": 23,
            "winpct": 52,
            "losepct": 47,
            "tiepct": 0,
            "winpctB": 40,
            "losepctB": 60,
            "tiepctB": 0,
            "winpctW": 61,
            "losepctW": 38,
            "tiepctW": 0
        },
        "PMC": {
            "wins": 43,
            "winsB": 17,
            "winsW": 26,
            "losses": 43,
            "lossesB": 26,
            "lossesW": 17,
            "ties": 0,
            "tiesB": 0,
            "tiesW": 0,
            "total": 86,
            "winpct": 50,
            "winpctB": 39,
            "losepct": 50,
            "losepctW": 39,
            "losepctB": 60,
            "tiepct": 0,
            "tiepctW": 0,
            "winpctW": 60,
            "tiepctB": 0
        },
        "MCTS": {
            "wins": 11,
            "winsB": 7,
            "winsW": 4,
            "losses": 42,
            "lossesB": 17,
            "lossesW": 25,
            "ties": 0,
            "tiesB": 0,
            "tiesW": 0,
            "total": 53,
            "winpct": 20,
            "winpctB": 0,
            "losepct": 79,
            "losepctW": 86,
            "losepctB": 0,
            "tiepct": 0,
            "tiepctW": 0,
            "winpctW": 13,
            "tiepctB": 0
        },
        "ab": {
            "wins": 23,
            "winsB": 15,
            "winsW": 8,
            "losses": 32,
            "lossesB": 12,
            "lossesW": 20,
            "ties": 0,
            "tiesB": 0,
            "tiesW": 0,
            "total": 55,
            "winpct": 41,
            "winpctB": 55,
            "losepct": 58,
            "losepctW": 50,
            "losepctB": 44,
            "tiepct": 0,
            "tiepctW": 0,
            "winpctW": 50,
            "tiepctB": 0
        }
    },
    "MCTS": {
        "GREEDY_MAJ": {
            "wins": 7,
            "winsB": 4,
            "winsW": 3,
            "losses": 0,
            "lossesB": 0,
            "lossesW": 0,
            "ties": 0,
            "tiesB": 0,
            "tiesW": 0,
            "total": 7,
            "winpct": 100,
            "losepct": 0,
            "tiepct": 0,
            "winpctB": 100,
            "losepctB": 0,
            "tiepctB": 0,
            "winpctW": 100,
            "losepctW": 0,
            "tiepctW": 0
        },
        "RANDOM": {
            "wins": 6,
            "winsB": 3,
            "winsW": 3,
            "losses": 2,
            "lossesB": 1,
            "lossesW": 1,
            "ties": 0,
            "tiesB": 0,
            "tiesW": 0,
            "total": 8,
            "winpct": 75,
            "losepct": 25,
            "tiepct": 0,
            "winpctW": 75,
            "losepctW": 25,
            "tiepctW": 0,
            "winpctB": 75,
            "losepctB": 25,
            "tiepctB": 0
        },
        "GREEDY_WMAJ": {
            "wins": 30,
            "winsB": 12,
            "winsW": 18,
            "losses": 12,
            "lossesB": 9,
            "lossesW": 3,
            "ties": 0,
            "tiesB": 0,
            "tiesW": 0,
            "total": 42,
            "winpct": 71,
            "losepct": 28,
            "tiepct": 0,
            "winpctB": 57,
            "losepctB": 42,
            "tiepctB": 0,
            "winpctW": 85,
            "losepctW": 14,
            "tiepctW": 0
        },
        "PMC": {
            "wins": 42,
            "winsB": 17,
            "winsW": 25,
            "losses": 11,
            "lossesB": 8,
            "lossesW": 3,
            "ties": 0,
            "tiesB": 0,
            "tiesW": 0,
            "total": 53,
            "winpct": 79,
            "winpctB": 68,
            "losepct": 20,
            "losepctW": 0,
            "losepctB": 32,
            "tiepct": 0,
            "tiepctW": 0,
            "winpctW": 0,
            "tiepctB": 0
        },
        "MCTS": {
            "wins": 44,
            "winsB": 17,
            "winsW": 27,
            "losses": 44,
            "lossesB": 27,
            "lossesW": 17,
            "ties": 0,
            "tiesB": 0,
            "tiesW": 0,
            "total": 88,
            "winpct": 50,
            "winpctB": 38,
            "losepct": 50,
            "losepctW": 38,
            "losepctB": 61,
            "tiepct": 0,
            "tiepctW": 0,
            "winpctW": 61,
            "tiepctB": 0
        },
        "ab": {
            "wins": 43,
            "winsB": 25,
            "winsW": 18,
            "losses": 22,
            "lossesB": 7,
            "lossesW": 15,
            "ties": 0,
            "tiesB": 0,
            "tiesW": 0,
            "total": 65,
            "winpct": 66,
            "winpctB": 0,
            "losepct": 33,
            "losepctW": 45,
            "losepctB": 0,
            "tiepct": 0,
            "tiepctW": 0,
            "winpctW": 54,
            "tiepctB": 0
        }
    },
    "ab": {
        "GREEDY_MAJ": {
            "wins": 7,
            "winsB": 2,
            "winsW": 5,
            "losses": 4,
            "lossesB": 3,
            "lossesW": 1,
            "ties": 0,
            "tiesB": 0,
            "tiesW": 0,
            "total": 11,
            "winpct": 63,
            "losepct": 36,
            "tiepct": 0,
            "winpctB": 40,
            "losepctB": 60,
            "tiepctB": 0,
            "winpctW": 83,
            "losepctW": 16,
            "tiepctW": 0
        },
        "RANDOM": {
            "wins": 3,
            "winsB": 2,
            "winsW": 1,
            "losses": 2,
            "lossesB": 1,
            "lossesW": 1,
            "ties": 1,
            "tiesB": 1,
            "tiesW": 0,
            "total": 6,
            "winpct": 50,
            "losepct": 33,
            "tiepct": 16,
            "winpctB": 50,
            "losepctB": 25,
            "tiepctB": 25,
            "winpctW": 50,
            "losepctW": 50,
            "tiepctW": 0
        },
        "GREEDY_WMAJ": {
            "wins": 6,
            "winsB": 4,
            "winsW": 2,
            "losses": 15,
            "lossesB": 9,
            "lossesW": 6,
            "ties": 1,
            "tiesB": 1,
            "tiesW": 0,
            "total": 22,
            "winpct": 27,
            "losepct": 68,
            "tiepct": 4,
            "winpctB": 28,
            "losepctB": 64,
            "tiepctB": 7,
            "winpctW": 25,
            "losepctW": 75,
            "tiepctW": 0
        },
        "PMC": {
            "wins": 32,
            "winsB": 12,
            "winsW": 20,
            "losses": 23,
            "lossesB": 14,
            "lossesW": 9,
            "ties": 0,
            "tiesB": 0,
            "tiesW": 0,
            "total": 55,
            "winpct": 58,
            "winpctB": 50,
            "losepct": 41,
            "losepctW": 31,
            "losepctB": 50,
            "tiepct": 0,
            "tiepctW": 0,
            "winpctW": 68,
            "tiepctB": 0
        },
        "MCTS": {
            "wins": 22,
            "winsB": 7,
            "winsW": 15,
            "losses": 43,
            "lossesB": 26,
            "lossesW": 17,
            "ties": 0,
            "tiesB": 0,
            "tiesW": 0,
            "total": 65,
            "winpct": 33,
            "winpctB": 21,
            "losepct": 66,
            "losepctW": 0,
            "losepctB": 78,
            "tiepct": 0,
            "tiepctW": 0,
            "winpctW": 0,
            "tiepctB": 0
        },
        "ab": {
            "wins": 43,
            "winsB": 17,
            "winsW": 26,
            "losses": 43,
            "lossesB": 26,
            "lossesW": 17,
            "ties": 0,
            "tiesB": 0,
            "tiesW": 0,
            "total": 86,
            "winpct": 50,
            "winpctB": 39,
            "losepct": 50,
            "losepctW": 39,
            "losepctB": 60,
            "tiepct": 0,
            "tiepctW": 0,
            "winpctW": 60,
            "tiepctB": 0
        }
    }
}